criipto_signatures/__init__.py
criipto_signatures/models.py
criipto_signatures/operations.py
criipto_signatures/py.typed
criipto_signatures/sample-form.pdf
criipto_signatures/sample.pdf
criipto_signatures/sdk.py
criipto_signatures/test_models.py
criipto_signatures/test_sdk.py
criipto_signatures/utils.py
criipto_signatures-1.29.1.dist-info/WHEEL
criipto_signatures-1.29.1.dist-info/METADATA
criipto_signatures-1.29.1.dist-info/RECORD
