Metadata-Version: 2.4
Name: criipto-signatures
Version: 1.29.1
Summary: A library for interacting with the Criipto signatures GraphQL API.
Author: Jan Aagaard Meier
Author-email: Jan Aagaard Meier <jan.meier@criipto.com>
License-Expression: MIT
Classifier: Development Status :: 3 - Alpha
Classifier: License :: OSI Approved :: MIT License
Requires-Dist: gql[httpx]>=4.0.0
Requires-Dist: httpx>=0.28.1
Requires-Dist: pydantic>=2.11.7
Requires-Python: >=3.13
Project-URL: changelog, https://github.com/criipto/criipto-signatures-sdk/releases
Project-URL: homepage, https://criipto.com
Project-URL: issues, https://github.com/criipto/criipto-signatures-sdk/issues
Project-URL: source, https://github.com/criipto/criipto-signatures-sdk/tree/master/packages/python
